{
    "Country Slug": "north-macedonia",
    "Country Name": "North Macedonia",
    "countryInfo": {
        "analytics_identifier": null,
        "base_path": "/foreign-travel-advice/north-macedonia",
        "content_id": "269306a3-45ab-4d96-a004-9abfcb7f7972",
        "description": "Latest FCDO travel advice for North Macedonia including on entry requirements, safety and security and local laws and customs.",
        "details": {
            "alert_status": [],
            "change_description": "This travel advice has been rewritten to make it easier to read and understand.",
            "change_history": [
                {
                    "note": "Latest update: Health Section \u2013 revised guidance on sources of health information before travel\r\n",
                    "public_timestamp": "2018-11-30T06:51:41.463Z"
                },
                {
                    "note": "Latest update: Health section - addition of information on air pollution ",
                    "public_timestamp": "2019-01-30T12:31:35.541Z"
                },
                {
                    "note": "Latest update: Terrorism section - addition of information about raids carried out by authorities in the Republic of North Macedonia on 15 February",
                    "public_timestamp": "2019-02-22T19:06:40.314Z"
                },
                {
                    "note": "Latest update: Health section - updated information on documents needed to receive free emergency treatment under the reciprocal healthcare agreement",
                    "public_timestamp": "2019-03-22T18:16:50.279Z"
                },
                {
                    "note": "Latest update: Safety and security section (Local travel) - His Holiness Pope Frances will visit the Republic of North Macedonia on 7 May 2019; during the visit, the Pope will visit a number of locations in Skopje, and conduct a Holy Mass in the central Square Macedonia; traffic restrictions are expected from 6am until 7pm; local authorities advise that public transport will be free of charge in Skopje, and encourage those travelling to Skopje from other towns in North Macedonia to use the railway; enhanced security restrictions will be in place; it's  advisable that you carry ID with you at all times",
                    "public_timestamp": "2019-05-02T08:26:45.212Z"
                },
                {
                    "note": "Latest update: This advice has been re-published with editorial amendment; Safety and security section (Local travel) - His Holiness Pope Francis will visit the Republic of North Macedonia on 7 May 2019",
                    "public_timestamp": "2019-05-02T11:28:38.617Z"
                },
                {
                    "note": "Latest update: Safety and security section (Local travel) - removal of information on visit of His Holiness Pope Francis to the Republic of North Macedonia on 7 May 2019",
                    "public_timestamp": "2019-05-08T13:42:28.517Z"
                },
                {
                    "note": "Safety and security section (Road travel) - updated information on licence requirements if driving in North Macedonia and neighbouring countries",
                    "public_timestamp": "2019-08-21T13:44:08.000Z"
                },
                {
                    "note": "Addition of information and advice on coronavirus (COVID-19) ('Health' and 'Summary' pages)\r\n",
                    "public_timestamp": "2020-02-27T14:51:57.000Z"
                },
                {
                    "note": "Addition of information on requirement to self-isolate for travellers from a number of countries including the UK. ('Summary' and 'Health' pages)",
                    "public_timestamp": "2020-03-12T16:05:32.000Z"
                },
                {
                    "note": "Addition of further information about travel restrictions ('Summary,' 'Entry requirements' and 'Health' pages)",
                    "public_timestamp": "2020-03-13T22:13:12.000Z"
                },
                {
                    "note": "Addition of further information about travel restrictions ('Summary,' 'Entry requirements' and 'Health' pages)",
                    "public_timestamp": "2020-03-14T22:36:26.000Z"
                },
                {
                    "note": "Update to restrictions for foreign nationals (Summary and Health)",
                    "public_timestamp": "2020-03-14T23:20:05.000Z"
                },
                {
                    "note": "The Foreign and Commonwealth Office (FCO) advise against all  but essential travel to North Macedonia due to the ongoing coronavirus (COVID-19) pandemic.",
                    "public_timestamp": "2020-03-16T20:31:49.000Z"
                },
                {
                    "note": "Update regarding border crossings closure and within 48 hours the main airport  ('Summary' and 'Health') ",
                    "public_timestamp": "2020-03-16T23:14:03.000Z"
                },
                {
                    "note": "Update regarding State of Emergency and airport closure ('Summary' and 'Health') ",
                    "public_timestamp": "2020-03-19T19:59:04.000Z"
                },
                {
                    "note": "Update to information and advice on coronavirus (COVID-19). Restrictive measures include a curfew on the whole territory of North Macedonia from 9pm to 6am from 22 March. ('Summary' page)",
                    "public_timestamp": "2020-03-22T10:53:29.000Z"
                },
                {
                    "note": "Information and advice on coronavirus (COVID-19). Restrictive measures include a curfew on the whole territory of North Macedonia from 9pm to 6am from 22 March. ('Summary' page)",
                    "public_timestamp": "2020-03-22T12:13:47.000Z"
                },
                {
                    "note": "Information and advice on coronavirus (COVID-19).   New restrictive measures include a curfew on the whole territory of North Macedonia from 9pm to 5am, and new restrictions on movements of people under the age of 18 years and those over 67 years from 24 March ('Summary' page)",
                    "public_timestamp": "2020-03-24T20:47:52.000Z"
                },
                {
                    "note": "Update on restrictions on the movement of all citizens in the whole territory of North Macedonia during the weekends. Also on new restrictive measures in Kumanovo. (Summary and Coronavirus)",
                    "public_timestamp": "2020-03-26T20:40:40.000Z"
                },
                {
                    "note": "Updated information on local measures introduced to combat the spread of coronavirus (COVID-19) and updated advice on options for returning to the UK ('Coronavirus' and 'Return to the UK' page)",
                    "public_timestamp": "2020-04-07T13:49:28.000Z"
                },
                {
                    "note": "Updated information on local measures introduced to combat the spread of coronavirus (COVID-19) including a curfew over the upcoming public holiday and increased restrictions on those entering the country. ('Coronavirus' page)",
                    "public_timestamp": "2020-04-14T15:03:19.000Z"
                },
                {
                    "note": "Update regarding State of Emergency ('Coronavirus' page)",
                    "public_timestamp": "2020-04-16T16:05:56.000Z"
                },
                {
                    "note": "Updated information on changes to restrictions including curfew hours, and masks/face coverings. ('Coronavirus' page)",
                    "public_timestamp": "2020-04-23T16:19:53.000Z"
                },
                {
                    "note": "Updated information on changes to restrictions over the upcoming public holiday weekend ('Coronavirus' page).",
                    "public_timestamp": "2020-04-29T13:16:06.000Z"
                },
                {
                    "note": " Updated information on local measures to combat the spread of coronavirus including curfew hours. ('Staying during Coronavirus' page).",
                    "public_timestamp": "2020-05-14T16:39:47.000Z"
                },
                {
                    "note": "Updated information on local measures to combat the spread of coronavirus including curfew times and State of Emergency. ('Staying during Coronavirus' page).",
                    "public_timestamp": "2020-05-15T17:59:35.000Z"
                },
                {
                    "note": "Updated information on options for returning to the UK, and on period of residence. (\u2018Return to the UK' and 'Staying during coronavirus' pages)",
                    "public_timestamp": "2020-05-19T16:33:18.000Z"
                },
                {
                    "note": "Addition of information and advice on financial support (\u2018Staying during coronavirus\u2019 page)",
                    "public_timestamp": "2020-05-20T11:49:30.000Z"
                },
                {
                    "note": "Updated information on changes to curfew over the public holiday weekend, 23 to 25 May ('Staying during coronavirus\u2019 page)",
                    "public_timestamp": "2020-05-22T20:55:25.000Z"
                },
                {
                    "note": "Updated information on measures for entering the country (\u2018Entry requirements\u2019 page)",
                    "public_timestamp": "2020-05-23T16:35:19.000Z"
                },
                {
                    "note": "Updated information on local measures to combat the spread of coronavirus including end of curfew and reopening of restaurants (See \u2018Staying during Coronavirus\u2019 and \u2018Summary\u2019 pages)",
                    "public_timestamp": "2020-05-28T11:30:49.000Z"
                },
                {
                    "note": "Update to information on an extension to the State of Emergency ('Staying during coronavirus' page)",
                    "public_timestamp": "2020-06-01T12:06:31.000Z"
                },
                {
                    "note": "Updated information on local measures to combat the spread of coronavirus including new curfew hours ('Staying during coronavirus' page)",
                    "public_timestamp": "2020-06-04T14:40:20.000Z"
                },
                {
                    "note": "New information on rules for entering the UK from 8 June.  ('Return to the UK' page)",
                    "public_timestamp": "2020-06-08T11:55:35.000Z"
                },
                {
                    "note": "Updated information on local measures to combat the spread of coronavirus ('Staying during coronavirus' page)",
                    "public_timestamp": "2020-06-12T16:19:31.000Z"
                },
                {
                    "note": "Addition of information on new transit rules (\u2018Entry requirements\u2019 page)",
                    "public_timestamp": "2020-06-15T14:05:57.000Z"
                },
                {
                    "note": "Addition of information on date of Parliamentary elections (\u2018Safety and Security\u2019 page) ",
                    "public_timestamp": "2020-06-16T15:46:55.000Z"
                },
                {
                    "note": "Update to information on local measures to combat the spread of coronavirus including reopening of land borders ('Return to the UK' and \u2018Entry Requirements\u2019 pages)",
                    "public_timestamp": "2020-06-17T16:11:38.000Z"
                },
                {
                    "note": "Update to information on local measures to combat the spread of coronavirus including  restrictions at land borders (\u2018Entry Requirements\u2019 pages)",
                    "public_timestamp": "2020-06-19T14:29:57.000Z"
                },
                {
                    "note": "Update to information on opening of land borders, airports and social facilities ('Return to the UK', \u2018Staying during coronavirus\u2019 and \u2018Entry requirements\u2019 pages)",
                    "public_timestamp": "2020-06-26T13:58:21.000Z"
                },
                {
                    "note": "Update to information and advice on the threat from terrorism in North Macedonia, reflecting an increased threat (\u2018Terrorism\u2019 and \u2018Summary\u2019 pages).  Addition of information on the opening of Skopje and Ohrid airports ('Return to the UK' page)",
                    "public_timestamp": "2020-07-10T12:53:39.000Z"
                },
                {
                    "note": "Update to information on the response of authorities in the Republic of North Macedonia to suspected terrorism.  ('Terrorism' page)",
                    "public_timestamp": "2020-09-02T16:23:09.000Z"
                },
                {
                    "note": "Editorial review to remove \u2018Return to the UK\u2019 section and improve \u2018Coronavirus\u2019 section",
                    "public_timestamp": "2020-09-04T15:37:26.000Z"
                },
                {
                    "note": "Update to information and advice on the threat from terrorism in North Macedonia, reflecting a decreased threat (\u2018Terrorism\u2019 and \u2018Summary\u2019 pages). Removal of information on the July parliamentary elections ",
                    "public_timestamp": "2020-09-29T15:52:30.000Z"
                },
                {
                    "note": "Update to information on the use of face masks in public places ('Coronavirus' page).",
                    "public_timestamp": "2020-10-30T16:53:31.000Z"
                },
                {
                    "note": "Revised assessment on the increased risk of terrorist attacks in North Macedonia ('Summary' and 'Terrorism' pages)",
                    "public_timestamp": "2020-11-11T18:16:10.000Z"
                },
                {
                    "note": "Addition of information and advice about Christmas markets and events over the festive period ('Summary' page).",
                    "public_timestamp": "2020-11-19T17:02:42.000Z"
                },
                {
                    "note": "Updated information on the threat from terrorism in North Macedonia, reflecting a decreased threat ('Summary' and \u2018Terrorism\u2019 pages)",
                    "public_timestamp": "2020-11-26T16:47:50.000Z"
                },
                {
                    "note": "New information and advice on flights to and from the UK ('Summary', \u2018Coronavirus' and 'Entry requirements' pages)",
                    "public_timestamp": "2020-12-21T22:25:42.000Z"
                },
                {
                    "note": "Addition of new information and advice on flights to and from the UK ('Summary', \u2018Coronavirus' and 'Entry Requirements' pages)",
                    "public_timestamp": "2020-12-22T18:18:01.000Z"
                },
                {
                    "note": "New information on entry requirements for North Macedonia; On 30 December, North Macedonia cancelled a ban on direct flights from the UK and The government has cancelled the requirement for passengers arriving from the UK to self-isolate on the basis of their travel history - no PCR test is required ('Summary', 'Coronavirus' and 'Entry requirements' pages)",
                    "public_timestamp": "2020-12-31T12:52:53.000Z"
                },
                {
                    "note": "Removal of out of date information on entry requirements for North Macedonia ('Summary', 'Coronavirus' and 'Entry requirements' pages).",
                    "public_timestamp": "2021-02-03T12:26:24.000Z"
                },
                {
                    "note": "Information about COVID-19 vaccines if you live in North Macedonia ('Coronavirus' page)",
                    "public_timestamp": "2021-02-23T09:51:13.000Z"
                },
                {
                    "note": "Updated information on the introduction of a curfew in North Macedonia ('Coronavirus' page)",
                    "public_timestamp": "2021-03-11T16:30:59.000Z"
                },
                {
                    "note": "Updated information on the extended curfew and introduction of new measures in North Macedonia ('Coronavirus' page)",
                    "public_timestamp": "2021-04-07T08:40:25.000Z"
                },
                {
                    "note": "Update to information on curfew and measures in North Macedonia ('Coronavirus' page)",
                    "public_timestamp": "2021-04-28T11:50:01.000Z"
                },
                {
                    "note": "New information on international travel requirements for travellers arriving from India or Brazil and updated information on COVID-19 restrictions for public places and services in North Macedonia ('Coronavirus' page)",
                    "public_timestamp": "2021-05-05T14:31:28.000Z"
                },
                {
                    "note": "Updated information on curfew hours and COVID-19 restrictions for public places and services in North Macedonia ('Coronavirus' page)",
                    "public_timestamp": "2021-05-14T09:05:26.000Z"
                },
                {
                    "note": "Removal of information on international travel restrictions for travellers arriving from Africa and Brazil ('Coronavirus' page)",
                    "public_timestamp": "2021-05-26T08:48:44.000Z"
                },
                {
                    "note": "Updated information on COVID-19 restrictions for public places in North Macedonia ('Coronavirus' page)",
                    "public_timestamp": "2021-06-02T12:13:18.000Z"
                },
                {
                    "note": "Updated information on COVID-19 restrictions in North Macedonia ('Coronavirus' page)",
                    "public_timestamp": "2021-06-16T15:13:16.000Z"
                },
                {
                    "note": "The FCDO no longer advises against all but essential travel to North Macedonia, based on the current assessment of COVID-19 risks",
                    "public_timestamp": "2021-07-08T16:29:52.000Z"
                },
                {
                    "note": "Information about COVID-19 vaccines if you live in North Macedonia ('Coronavirus' page)",
                    "public_timestamp": "2021-07-19T11:31:31.000Z"
                },
                {
                    "note": "Information about forest fires ('Natural disasters' page)",
                    "public_timestamp": "2021-08-03T15:08:45.000Z"
                },
                {
                    "note": "Updated information about indoor and outdoor events ('Coronavirus' page)",
                    "public_timestamp": "2021-08-18T16:08:59.000Z"
                },
                {
                    "note": "New information about changes to entry requirements from 1 September ('Entry requirements\u2019 page)",
                    "public_timestamp": "2021-08-20T14:14:39.000Z"
                },
                {
                    "note": "Updated information on entry requirements from 1 September (see 'Entry requirements' pages)",
                    "public_timestamp": "2021-08-26T13:08:21.000Z"
                },
                {
                    "note": "Updated information on new entry and exit requirements ('Entry requirements' page)",
                    "public_timestamp": "2021-09-03T09:27:23.000Z"
                },
                {
                    "note": "Addition of information that people wanting to use the UK systems to demonstrate their COVID-19 status using a printed PDF version will need to ensure the printout is dated from 1 November ('Coronavirus' and 'Entry requirements' pages)",
                    "public_timestamp": "2021-11-03T12:22:44.000Z"
                },
                {
                    "note": " Updated information on North Macedonia's COVID-19 restrictions ('Coronavirus' page)",
                    "public_timestamp": "2021-11-16T12:48:33.000Z"
                },
                {
                    "note": "Addition of information and advice about Christmas markets and events over the festive period (\u2018Summary\u2019 page)",
                    "public_timestamp": "2021-11-26T11:24:38.000Z"
                },
                {
                    "note": "Update to changes to COVID measures ('Coronavirus\u2019 page) ",
                    "public_timestamp": "2022-05-03T15:38:05.000Z"
                },
                {
                    "note": "Update warning about major demonstrations announced to take place in Skopje; you should check local media for the latest information, remain vigilant and avoid any demonstrations ('Safety and security \u2013 Political situation page)",
                    "public_timestamp": "2022-07-07T17:43:17.000Z"
                },
                {
                    "note": "Update information about recent bomb threats in North Macedonia; you should follow the directions of the local authorities (See 'Terrorism' page)",
                    "public_timestamp": "2022-12-23T18:05:56.000Z"
                },
                {
                    "note": "Information about the global terrorism risks to British nationals abroad on all FCDO travel advice pages.",
                    "public_timestamp": "2023-06-22T09:34:20.000Z"
                },
                {
                    "note": "Information about the decreased terrorism risks to British nationals in North Macedonia ('Summary' and 'Terrorism' pages).",
                    "public_timestamp": "2023-07-19T14:44:37.000Z"
                },
                {
                    "note": "This travel advice has been rewritten to make it easier to read and understand.",
                    "public_timestamp": "2023-08-14T15:49:13.000Z"
                }
            ],
            "country": {
                "name": "North Macedonia",
                "slug": "north-macedonia",
                "synonyms": []
            },
            "email_signup_link": "/foreign-travel-advice/north-macedonia/email-signup",
            "max_cache_time": 10,
            "parts": [
                {
                    "body": "<p>The Foreign, Commonwealth &amp; Development Office (<abbr title=\"Foreign, Commonwealth &amp; Development Office\">FCDO</abbr>) provides advice about risks of travel to help British nationals make informed decisions. Find out <a href=\"https://www.gov.uk/guidance/about-foreign-commonwealth-development-office-travel-advice\">more about <abbr title=\"Foreign, Commonwealth &amp; Development Office\">FCDO</abbr> travel advice</a>.</p>\n\n<h2 id=\"before-you-travel\">Before you travel</h2>\n\n<p>No travel can be guaranteed safe. Read all the advice in this guide as well as <a href=\"https://www.gov.uk/government/collections/support-for-british-nationals-abroad\">support for British nationals abroad</a> which includes:</p>\n\n<ul>\n  <li>\n    <p>advice on preparing for travel abroad and reducing risks</p>\n  </li>\n  <li>\n    <p>information for women, LGBT+ and disabled travellers</p>\n  </li>\n</ul>\n\n<p>Follow and contact <abbr title=\"Foreign, Commonwealth &amp; Development Office\">FCDO</abbr> travel on <a rel=\"external\" href=\"https://twitter.com/fcdotravelgovuk\">Twitter</a>, <a rel=\"external\" href=\"https://www.facebook.com/fcdotravel\">Facebook</a> and <a rel=\"external\" href=\"https://www.instagram.com/travelaware/\">Instagram</a>. You can also sign up to <a href=\"https://www.gov.uk/foreign-travel-advice/north-macedonia/email-signup\">get email notifications</a> when this advice is updated.</p>\n\n<h3 id=\"travel-insurance\">Travel insurance</h3>\n\n<p>If you choose to travel, research your destinations and <a href=\"https://www.gov.uk/guidance/foreign-travel-insurance\">get appropriate travel insurance</a>. Insurance should cover your itinerary, planned activities and expenses in an emergency.</p>\n\n",
                    "slug": "warnings-and-insurance",
                    "title": "Warnings and insurance"
                },
                {
                    "body": "<p>This advice reflects the UK government\u2019s understanding of current rules for people travelling on a full <a href=\"https://www.gov.uk/types-of-british-nationality\">\u2018British citizen\u2019 passport</a> from the UK, for the most common types of travel.</p>\n\n<p>The authorities in North Macedonia set and enforce entry rules. If you\u2019re not sure how these requirements apply to you, contact the <a rel=\"external\" href=\"https://london.mfa.gov.mk/en\">North Macedonian Embassy in the UK</a>.</p>\n\n<h2 id=\"covid-19-rules\">COVID-19 rules</h2>\n\n<p>There are no COVID-19 testing or vaccination requirements for passengers entering North Macedonia.</p>\n\n<h2 id=\"passport-validity-requirements\">Passport validity requirements</h2>\n\n<p>Make sure your passport is valid for at least 90 days from your date of entry into North Macedonia.</p>\n\n<h2 id=\"visa-requirements\">Visa requirements</h2>\n\n<p>You can visit North Macedonia for up to 3 months without a visa.</p>\n\n<h3 id=\"travelling-with-children\">Travelling with children</h3>\n\n<p>Children need an extra (officially stamped) document signed by their parents, second parent or legal guardian(s) if they\u2019re travelling:</p>\n\n<ul>\n  <li>alone</li>\n  <li>with only one parent</li>\n  <li>with an adult who is not their legal guardian</li>\n</ul>\n\n<p>Third countries you are transiting may also have their own rules. If travelling by air, you should also check with your airline as many have their own specific forms for this purpose.</p>\n\n<h3 id=\"uk-refugee-travel-documents\">UK refugee travel documents</h3>\n\n<p>If you hold a UK refugee travel document, you must have a visa to travel to North Macedonia. You will also need a visa to travel through North Macedonia on your way to Kosovo. You can apply for a visa from the <a rel=\"external\" href=\"https://london.mfa.gov.mk/en\">North Macedonian Embassy in the UK</a>.</p>\n\n<h3 id=\"applying-for-a-visa\">Applying for a visa</h3>\n\n<p>If you plan to stay for longer than 3 months, contact the <a rel=\"external\" href=\"https://london.mfa.gov.mk/en\">North Macedonian Embassy in the UK</a>.</p>\n\n<h2 id=\"registering-with-the-police\">Registering with the police</h2>\n\n<p>You must register with the local police in the town or city where you\u2019re staying within 48 hours of your arrival in North Macedonia. If you\u2019re staying in a hotel, staff will register you at check-in. Keep the registration document with you until you leave North Macedonia. If you have registered with the police directly you must de-register 24 hours before you leave the country.</p>\n\n<p>If you do not get registered, you may face:</p>\n\n<ul>\n  <li>a fine</li>\n  <li>detention and a court hearing</li>\n  <li>a restriction on returning to North Macedonia</li>\n</ul>\n\n<h2 id=\"travelling-to-serbia\">Travelling to Serbia</h2>\n\n<p>Serbia has sometimes denied entry to people leaving North Macedonia with passport stamps from Kosovo.</p>\n\n<h2 id=\"vaccination-requirements\">Vaccination requirements</h2>\n\n<p>At least 8 weeks before your trip, <a rel=\"external\" href=\"https://travelhealthpro.org.uk/country/133/north-macedonia\">check the vaccinations and certificates you need in TravelHealthPro\u2019s North Macedonia guide</a>.</p>\n\n<h2 id=\"customs-rules\">Customs rules</h2>\n\n<p>There are strict rules about goods that can be brought into and taken out of North Macedonia. You can find more information from the <a rel=\"external\" href=\"https://customs.gov.mk/pocetna.nspx\">North Macedonia Customs Administration</a>. You must declare anything that may be prohibited or subject to tax or duty.</p>\n\n<h2 id=\"taking-money-into-north-macedonia\">Taking money into North Macedonia</h2>\n\n<p>You must declare any cash amount of foreign currency greater than 10,000 euros when you enter North Macedonia. If you do not, customs officers may detain you and seize the cash when you try to leave.</p>\n\n",
                    "slug": "entry-requirements",
                    "title": "Entry requirements"
                },
                {
                    "body": "<h2 id=\"terrorism\">Terrorism</h2>\n\n<p>There is a high threat of terrorist attack globally affecting UK interests and British nationals, including from groups and individuals who view the UK and British nationals as targets. You should remain vigilant at all times.</p>\n\n<p>UK Counter Terrorism Policing has information and advice on <a rel=\"external\" href=\"https://www.counterterrorism.police.uk/safetyadvice/\">staying safe abroad</a> and what to do in the event of a terrorist attack. Find out <a href=\"https://www.gov.uk/guidance/reduce-your-risk-from-terrorism-while-abroad\">how to reduce your risk from terrorism while abroad</a>.</p>\n\n<h3 id=\"terrorism-in-north-macedonia\">Terrorism in North Macedonia</h3>\n\n<p>Terrorist attacks in North Macedonia cannot be ruled out. Attacks could be indiscriminate, including in places visited by foreigners. Terrorists may target religious sites, including churches.</p>\n\n<p>The authorities in North Macedonia have carried out raids against suspected terrorists. There\u2019s a risk of terrorist attacks inspired by extremist ideology in North Macedonia.</p>\n\n<h2 id=\"political-situation\">Political situation</h2>\n\n<p>Occasional protests occur in North Macedonia which can cause disruption. You should check local media for the latest information, be vigilant, and avoid large crowds and gatherings.</p>\n\n<p>If there is civil disorder, stay indoors when possible, especially after dark, and avoid crowds and demonstrations.</p>\n\n<h2 id=\"crime\">Crime</h2>\n\n<p>Attacks against foreigners are extremely rare.</p>\n\n<p>Organised criminal groups are active, particularly in northern areas near the border with Kosovo.</p>\n\n<p>There are occasional shooting incidents, including in Skopje, but they are not targeted at foreigners. People sometimes fire guns when celebrating.</p>\n\n<h3 id=\"protecting-your-belongings\">Protecting your belongings</h3>\n\n<p>There have been several cases of pickpocketing by gangs of children and bag snatches in the main shopping and entertainment areas late at night. Foreign nationals appear to have been specifically targeted. Make sure your personal possessions are secure.</p>\n\n<p>Keep your passport in a secure place and carry a copy of your passport photo page for identification. If your passport is lost or stolen, report it to the local police and <a href=\"https://www.gov.uk/report-a-lost-or-stolen-passport\">cancel it immediately</a>.</p>\n\n<h2 id=\"laws-and-cultural-differences\">Laws and cultural differences</h2>\n\n<h3 id=\"using-cameras-and-binoculars-in-secure-areas\">Using cameras and binoculars in secure areas</h3>\n\n<p>It is illegal to take photographs of any military installation or site of government or strategic importance.</p>\n\n<h3 id=\"lgbt-travellers\">LGBT+ travellers</h3>\n\n<p>Same-sex sexual relationships are legal, but people in North Macedonia are not particularly open about them. LGBT+ bars and restaurants are not common.</p>\n\n<p>Read more <a href=\"https://www.gov.uk/lesbian-gay-bisexual-and-transgender-foreign-travel-advice\">advice for LGBT+ travellers</a>.</p>\n\n<h3 id=\"money\">Money</h3>\n\n<p>British banks do not exchange Macedonian denars, so exchange any unwanted denars before you leave. You should only change money through banks or official exchanges and not through street dealers. You will not be able to exchange Scottish and Northern Irish banknotes.</p>\n\n<h2 id=\"outdoor-activities-and-adventure-tourism\">Outdoor activities and adventure tourism</h2>\n\n<h3 id=\"swimming-safety\">Swimming safety</h3>\n\n<p>Lakes Ohrid, Prespa and Dojran are suitable for swimming and recreation, according to the North Macedonian State Sanitary and Health Inspectorate.</p>\n\n<p>However, the authorities rate the rivers Vardar and Treska and Lake Treska as unsuitable for swimming.</p>\n\n<h2 id=\"transport-risks\">Transport risks</h2>\n\n<h3 id=\"local-travel\">Local travel</h3>\n\n<p>If you are travelling near the border with Kosovo, you should only travel on main roads and during daylight hours.</p>\n\n<p>Lorries crossing the North Macedonia border may be subject to long delays. Make sure you have the proper customs documentation before you arrive at the border.</p>\n\n<p>Between November and February, Skopje and surrounding areas can experience thick fog. There can be flight delays and diversions if fog affects visibility at Skopje airport.</p>\n\n<p>You can find flight information on the <a rel=\"external\" href=\"https://skp.airports.com.mk/en-EN/\">Skopje International Airport</a> website.</p>\n\n<h2 id=\"road-travel\">Road travel</h2>\n\n<p>If you are planning to drive in North Macedonia, see information on <a href=\"https://www.gov.uk/driving-abroad\">driving abroad</a> and read the <a rel=\"external\" href=\"https://www.rac.co.uk/drive/travel/country/macedonia/\">RAC guide</a>.</p>\n\n<h3 id=\"licences-and-permits\">Licences and permits</h3>\n\n<p>You need\u202feither a 1968 <a href=\"https://www.gov.uk/driving-abroad/international-driving-permit\">international driving permit (IDP)</a> or a valid UK driving licence\u202fto drive in North Macedonia. The 1949 IDP is not accepted any more. You cannot buy an IDP outside the UK, so get one before you travel. You can buy an IDP in person from some UK post offices \u2013 <a rel=\"external\" href=\"https://www.postoffice.co.uk/identity/international-driving-permit#bf-full-width\">find your nearest post office branch</a> that offers this service.</p>\n\n<h3 id=\"driving-a-british-car-in-north-macedonia\">Driving a British car in North Macedonia</h3>\n\n<p>If you are taking your own car, you must have:</p>\n\n<ul>\n  <li>vehicle registration</li>\n  <li>ownership documents</li>\n  <li>valid insurance to drive in North Macedonia. Check your insurance covers you to drive in North Macedonia and you are able to show proof to border officials. A green card might be helpful to demonstrate you have the correct cover.</li>\n</ul>\n\n<h3 id=\"driving-regulations\">Driving regulations</h3>\n\n<p>Road conditions and driving standards vary widely. Driving styles differ significantly from those in UK. There are frequent accidents. Take care at all times while driving or on foot.</p>\n\n<p>If you have an accident, do not move your vehicle until the police record the incident and allow you to do so. In case of emergency, contact:</p>\n\n<ul>\n  <li>police: 192</li>\n  <li>\n    <p>ambulance: 194</p>\n  </li>\n  <li>roadside assistance: 196</li>\n</ul>\n\n<p>The legal drink drive limit in North Macedonia is lower than in some parts of the UK. The blood alcohol limit is 50 milligrammes of alcohol per 100 millilitres of blood, or 0.5 milligrammes per millilitre. If you drink and drive you risk a heavy fine and the possibility of arrest. There is a policy of zero tolerance for professional (eg HGV) drivers.</p>\n\n<p>You can be fined for offences including (but not limited to):</p>\n\n<ul>\n  <li>not using side lights or dipped headlights, including during the day</li>\n  <li>using a mobile phone while driving</li>\n  <li>not wearing a seatbelt, as both a driver and a passenger</li>\n  <li>not having all the required safety equipment, including snow chains where conditions require them</li>\n</ul>\n\n<p>When travelling on major roads, you can pay the toll fare in Macedonian denars or in euros by using cash or a credit card.</p>\n\n<h2 id=\"extreme-weather-and-natural-disasters\">Extreme weather and natural disasters</h2>\n\n<h3 id=\"forest-fires\">Forest fires</h3>\n\n<p>Forest fires can happen during summer months. Check on the outbreak of fires with local media and follow any instructions from local authorities.</p>\n\n<p>In the summer months there may be bans on movement in forest areas to help prevent fires. Follow advice from local authorities. If you ignore the ban, you may get a fine.</p>\n\n<h3 id=\"earthquakes\">Earthquakes</h3>\n\n<p>Earthquakes occasionally occur. You should familiarise yourself with <a rel=\"external\" href=\"https://www.ready.gov/earthquakes\">steps to take in the event of further seismic shocks</a>.</p>\n\n",
                    "slug": "safety-and-security",
                    "title": "Safety and security"
                },
                {
                    "body": "<p>Before you travel check that:</p>\n\n<ul>\n  <li>your destination can provide the healthcare you may need</li>\n  <li>you have <a href=\"https://www.gov.uk/guidance/foreign-travel-insurance\">appropriate travel insurance</a> for local treatment or unexpected medical evacuation</li>\n</ul>\n\n<p>This is particularly important if you have a health condition or are pregnant.</p>\n\n<h2 id=\"emergency-medical-number\">Emergency medical number</h2>\n\n<p>Dial 194 and ask for an ambulance.</p>\n\n<p>Contact your insurance or medical assistance company promptly if you\u2019re referred to a medical facility for treatment.</p>\n\n<h2 id=\"vaccinations-and-health-risks\">Vaccinations and health risks</h2>\n\n<p>At least 8 weeks before your trip check:</p>\n\n<ul>\n  <li>the latest information on vaccinations and health risks in <a rel=\"external\" href=\"https://travelhealthpro.org.uk/country/133/north-macedonia\">TravelHealthPro\u2019s North Macedonia guide</a>\n</li>\n  <li>where to get vaccines and whether you have to pay on the <a rel=\"external\" href=\"https://www.nhs.uk/conditions/travel-vaccinations/\">NHS travel vaccinations page</a>\n</li>\n</ul>\n\n<p>Mosquito-borne diseases including West Nile virus are present in North Macedonia.</p>\n\n<p>High levels of air pollution in cities, especially in winter, can affect public health. Children, the elderly and those with pre-existing medical conditions may be especially affected. You can find more information and advice on air quality on the <a rel=\"external\" href=\"https://www.who.int/airpollution/en/\">World Health Organization (WHO)</a> website. Keep up to date with local information and seek medical advice on appropriate precautions.</p>\n\n<h2 id=\"medication\">Medication</h2>\n\n<p>The legal status and regulation of some medicines prescribed or bought in the UK can be different in other countries.</p>\n\n<p>Read <a rel=\"external\" href=\"https://travelhealthpro.org.uk/factsheet/43/medicines-abroad\">best practice when travelling with medicines on TravelHealthPro</a>.</p>\n\n<p>The NHS has information on <a rel=\"external\" href=\"https://www.nhs.uk/common-health-questions/medicines/can-i-take-my-medicine-abroad/\">whether you can take your medicine abroad</a>.</p>\n\n<h2 id=\"accessing-and-paying-for-healthcare\">Accessing and paying for healthcare</h2>\n\n<p>There is a reciprocal healthcare agreement for British nationals, which entitles you to free emergency treatment in North Macedonia. Further details are available online at <a href=\"https://www.gov.uk/guidance/uk-reciprocal-healthcare-agreements-with-non-eu-countries#north-macedonia\">UK reciprocal healthcare agreements with non-EU countries</a>.</p>\n\n<p>There is a reciprocal healthcare agreement for British nationals, which entitles you to <a href=\"https://www.gov.uk/guidance/uk-reciprocal-healthcare-agreements-with-non-eu-countries#north-macedonia\">free emergency treatment in North Macedonia</a>.</p>\n\n<p>Make sure you have adequate insurance. You may need to pay for some treatment up-front and should familiarise yourself with your travel insurance policy and what that might cover.</p>\n\n<p><abbr title=\"Foreign, Commonwealth &amp; Development Office\">FCDO</abbr> has a <a href=\"https://www.gov.uk/government/publications/north-macedonia-list-of-medical-facilities\">list of English speaking doctors in North Macedonia</a>.</p>\n\n<h2 id=\"covid-19-healthcare-in-north-macedonia\">COVID-19 healthcare in North Macedonia</h2>\n\n<p>Check the latest information on risk from COVID-19 for North Macedonia on the <a rel=\"external\" href=\"https://travelhealthpro.org.uk/country/133/north-macedonia#COVID-19\">TravelHealthPro website</a></p>\n\n<p>See the TravelHealthPro website for further advice on <a rel=\"external\" href=\"https://travelhealthpro.org.uk/news/499/novel-coronavirus-covid-19-general-advice-for-travellers\">travel abroad and reducing spread of respiratory viruses during the COVID-19 pandemic</a>.</p>\n\n<h2 id=\"travel-and-mental-health\">Travel and mental health</h2>\n\n<p>Read <a href=\"https://www.gov.uk/guidance/foreign-travel-advice-for-people-with-mental-health-issues\"><abbr title=\"Foreign, Commonwealth &amp; Development Office\">FCDO</abbr> guidance on travel and mental health</a>. There is also <a rel=\"external\" href=\"https://travelhealthpro.org.uk/factsheet/85/travelling-with-mental-health-conditions\">mental health guidance on TravelHealthPro</a>.</p>\n\n",
                    "slug": "health",
                    "title": "Health"
                },
                {
                    "body": "<p>The Foreign, Commonwealth &amp; Development Office (<abbr title=\"Foreign, Commonwealth &amp; Development Office\">FCDO</abbr>) cannot provide tailored advice for individual trips. Read this travel advice and carry out your own research before deciding whether to travel.</p>\n\n<h2 id=\"emergency-services-in-north-macedonia\">Emergency services in North Macedonia</h2>\n\n<p>Ambulance: 194</p>\n\n<p>Police: 192</p>\n\n<p>Roadside assistance: 196</p>\n\n<h2 id=\"contact-your-travel-provider-and-insurer\">Contact your travel provider and insurer</h2>\n\n<p>Contact your travel provider and your insurer if you are involved in a serious incident or emergency abroad. They will tell you if they can help and what you need to do.</p>\n\n<h3 id=\"refunds-and-changes-to-travel\">Refunds and changes to travel</h3>\n\n<p>For refunds or changes to travel, contact your travel provider. You may also be able to make a claim through insurance. However, insurers usually require you to talk to your travel provider first.</p>\n\n<p>Find out more about <a href=\"https://www.gov.uk/guidance/about-foreign-commonwealth-development-office-travel-advice#changing-or-cancelling-travel-plans\">changing or cancelling travel plans</a>, including:</p>\n\n<ul>\n  <li>where to get advice if you are in a dispute with a provider</li>\n  <li>how to access previous versions of travel advice to support a claim</li>\n</ul>\n\n<h2 id=\"support-from-fcdo\">Support from <abbr title=\"Foreign, Commonwealth &amp; Development Office\">FCDO</abbr>\n</h2>\n\n<p><abbr title=\"Foreign, Commonwealth &amp; Development Office\">FCDO</abbr> has guidance on staying safe and what to do if you need help or support abroad, including:</p>\n\n<ul>\n  <li>finding English-speaking <a rel=\"external\" href=\"https://find-a-professional-service-abroad.service.csd.fcdo.gov.uk/results?serviceType=lawyers&amp;readNotice=ok&amp;region=Not%20set&amp;practiceArea=All&amp;readDisclaimer=ok&amp;country=North%20Macedonia\">lawyers</a>, <a href=\"https://www.gov.uk/government/publications/north-macedonia-funeral-directors/north-macedonia-list-of-funeral-directors\">funeral directors</a> and <a href=\"https://www.gov.uk/government/publications/north-macedonia-translators\">translators and interpreters</a> in North Macedonia</li>\n  <li>dealing with a <a href=\"https://www.gov.uk/guidance/when-someone-dies-in-north-macedonia\">death in North Macedonia</a>\n</li>\n  <li>being <a href=\"https://www.gov.uk/government/publications/north-macedonia-prisoner-pack\">arrested in North Macedonia</a>\n</li>\n  <li>getting help if you\u2019re a <a href=\"https://www.gov.uk/victim-crime-abroad\">victim of crime</a>\n</li>\n  <li>what to do if you\u2019re <a href=\"https://www.gov.uk/guidance/in-hospital-abroad\">in hospital</a>\n</li>\n  <li>if you\u2019re <a href=\"https://www.gov.uk/guidance/how-to-deal-with-a-crisis-overseas\">affected by a crisis</a>, such as a terrorist attack</li>\n</ul>\n\n<h2 id=\"contacting-fcdo\">Contacting <abbr title=\"Foreign, Commonwealth &amp; Development Office\">FCDO</abbr>\n</h2>\n\n<p>Follow and contact <abbr title=\"Foreign, Commonwealth &amp; Development Office\">FCDO</abbr> travel on <a rel=\"external\" href=\"https://twitter.com/fcdotravelgovuk\">Twitter</a>, <a rel=\"external\" href=\"https://www.facebook.com/fcdotravel\">Facebook</a> and <a rel=\"external\" href=\"https://www.instagram.com/travelaware/\">Instagram</a>. You can also sign up to <a href=\"https://www.gov.uk/foreign-travel-advice/north-macedonia/email-signup\">get email notifications</a> when this travel advice is updated.</p>\n\n<h3 id=\"help-in-north-macedonia-in-an-emergency\">Help in North Macedonia in an emergency</h3>\n\n<p>If you are in North Macedonia and you need emergency help from the UK government, contact the <a href=\"https://www.gov.uk/world/organisations/british-embassy-skopje\">British embassy in Skopje</a>.</p>\n\n<p>You can also <a rel=\"external\" href=\"https://www.contact-embassy.service.gov.uk/?country=North%20Macedonia&amp;post=British%20Embassy%20Skopje\">contact <abbr title=\"Foreign, Commonwealth &amp; Development Office\">FCDO</abbr> online</a>.</p>\n\n<h3 id=\"fcdo-in-london\">\n<abbr title=\"Foreign, Commonwealth &amp; Development Office\">FCDO</abbr> in London</h3>\n\n<p>You can call <abbr title=\"Foreign, Commonwealth &amp; Development Office\">FCDO</abbr> in London if you need urgent help because something has happened to a friend or relative abroad.</p>\n\n<p>Telephone: 020 7008 5000 (24 hours)</p>\n\n<p><a href=\"https://www.gov.uk/call-charges\">Find out about call charges</a></p>\n\n<h2 id=\"risk-information-for-british-companies\">Risk information for British companies</h2>\n\n<p>The <a href=\"https://www.gov.uk/government/collections/overseas-business-risk\">Overseas Business Risk service</a> offers information and advice for British companies operating overseas on how to manage political, economic, and business security-related risks.</p>\n\n",
                    "slug": "getting-help",
                    "title": "Getting help"
                }
            ],
            "reviewed_at": "2023-08-14T15:49:13Z",
            "updated_at": "2023-08-14T15:49:13Z"
        },
        "document_type": "travel_advice",
        "first_published_at": "2013-03-14T00:00:00Z",
        "links": {
            "available_translations": [
                {
                    "api_path": "/api/content/foreign-travel-advice/north-macedonia",
                    "api_url": "https://www.gov.uk/api/content/foreign-travel-advice/north-macedonia",
                    "base_path": "/foreign-travel-advice/north-macedonia",
                    "content_id": "269306a3-45ab-4d96-a004-9abfcb7f7972",
                    "document_type": "travel_advice",
                    "links": {},
                    "locale": "en",
                    "public_updated_at": "2023-08-14T15:49:13Z",
                    "schema_name": "travel_advice",
                    "title": "North Macedonia travel advice",
                    "web_url": "https://www.gov.uk/foreign-travel-advice/north-macedonia",
                    "withdrawn": false
                }
            ],
            "meets_user_needs": [
                {
                    "api_path": "/api/content/needs/know-what-the-government-s-official-travel-advice-is-to-a-country-or-part-of-a-country",
                    "api_url": "https://www.gov.uk/api/content/needs/know-what-the-government-s-official-travel-advice-is-to-a-country-or-part-of-a-country",
                    "base_path": "/needs/know-what-the-government-s-official-travel-advice-is-to-a-country-or-part-of-a-country",
                    "content_id": "5118d7b4-215d-45e6-bd20-15d7bc21314f",
                    "details": {
                        "benefit": "I can adjust my travel insurance policy accordingly",
                        "goal": "know what the government's official travel advice is to a country, or part of a country",
                        "justifications": [
                            "There is clear demand for it from users"
                        ],
                        "met_when": null,
                        "role": "travel insurance provider"
                    },
                    "document_type": "need",
                    "links": {},
                    "locale": "en",
                    "schema_name": "need",
                    "title": "As a travel insurance provider, I need to know what the government's official travel advice is to a country, or part of a country, so that I can adjust my travel insurance policy accordingly (101191)",
                    "web_url": "https://www.gov.uk/needs/know-what-the-government-s-official-travel-advice-is-to-a-country-or-part-of-a-country",
                    "withdrawn": false
                }
            ],
            "ordered_related_items": [
                {
                    "api_path": "/api/content/guidance/about-foreign-commonwealth-development-office-travel-advice",
                    "api_url": "https://www.gov.uk/api/content/guidance/about-foreign-commonwealth-development-office-travel-advice",
                    "base_path": "/guidance/about-foreign-commonwealth-development-office-travel-advice",
                    "content_id": "dd34d3a4-56bd-4cf5-b821-d76f9d997153",
                    "document_type": "detailed_guide",
                    "links": {},
                    "locale": "en",
                    "public_updated_at": "2023-09-29T07:47:58Z",
                    "schema_name": "detailed_guide",
                    "title": "About Foreign, Commonwealth & Development Office travel advice",
                    "web_url": "https://www.gov.uk/guidance/about-foreign-commonwealth-development-office-travel-advice",
                    "withdrawn": false
                },
                {
                    "api_path": "/api/content/government/collections/support-for-british-nationals-abroad",
                    "api_url": "https://www.gov.uk/api/content/government/collections/support-for-british-nationals-abroad",
                    "base_path": "/government/collections/support-for-british-nationals-abroad",
                    "content_id": "aad65646-964d-4f68-ac22-5bc6c8281336",
                    "document_type": "document_collection",
                    "links": {},
                    "locale": "en",
                    "public_updated_at": "2022-08-31T15:02:00Z",
                    "schema_name": "document_collection",
                    "title": "Support for British nationals abroad",
                    "web_url": "https://www.gov.uk/government/collections/support-for-british-nationals-abroad",
                    "withdrawn": false
                },
                {
                    "api_path": "/api/content/guidance/foreign-travel-checklist",
                    "api_url": "https://www.gov.uk/api/content/guidance/foreign-travel-checklist",
                    "base_path": "/guidance/foreign-travel-checklist",
                    "content_id": "5d8baf93-7631-11e4-a3cb-005056011aef",
                    "document_type": "detailed_guide",
                    "links": {},
                    "locale": "en",
                    "public_updated_at": "2023-08-29T14:12:45Z",
                    "schema_name": "detailed_guide",
                    "title": "Foreign travel checklist",
                    "web_url": "https://www.gov.uk/guidance/foreign-travel-checklist",
                    "withdrawn": false
                },
                {
                    "api_path": "/api/content/world/north-macedonia",
                    "api_url": "https://www.gov.uk/api/content/world/north-macedonia",
                    "base_path": "/world/north-macedonia",
                    "content_id": "b4c8cc2b-0fb0-4ec0-ba63-72c324f51b3a",
                    "description": "Services if you're visiting, studying, working or living in North Macedonia. Includes information about trading with and doing business in the UK and North Macedonia.",
                    "details": {
                        "internal_name": "UK help and services in North Macedonia",
                        "notes_for_editors": "",
                        "visible_to_departmental_editors": false
                    },
                    "document_type": "taxon",
                    "links": {},
                    "locale": "en",
                    "phase": "live",
                    "public_updated_at": "2019-02-22T17:11:25Z",
                    "schema_name": "taxon",
                    "title": "UK help and services in North Macedonia",
                    "web_url": "https://www.gov.uk/world/north-macedonia",
                    "withdrawn": false
                }
            ],
            "organisations": [
                {
                    "analytics_identifier": "D1315",
                    "api_path": "/api/content/government/organisations/foreign-commonwealth-development-office",
                    "api_url": "https://www.gov.uk/api/content/government/organisations/foreign-commonwealth-development-office",
                    "base_path": "/government/organisations/foreign-commonwealth-development-office",
                    "content_id": "f9fcf3fe-2751-4dca-97ca-becaeceb4b26",
                    "details": {
                        "acronym": "FCDO",
                        "brand": "foreign-commonwealth-development-office",
                        "default_news_image": {
                            "high_resolution_url": "https://assets.publishing.service.gov.uk/media/621e4de4e90e0710be0354d7/s960_fcdo-main-building.jpg",
                            "url": "https://assets.publishing.service.gov.uk/media/621e4de48fa8f5490aff83b4/s300_fcdo-main-building.jpg"
                        },
                        "logo": {
                            "crest": "single-identity",
                            "formatted_title": "Foreign, Commonwealth<br/>&amp; Development Office"
                        },
                        "organisation_govuk_status": {
                            "status": "live",
                            "updated_at": null,
                            "url": null
                        }
                    },
                    "document_type": "organisation",
                    "links": {},
                    "locale": "en",
                    "schema_name": "organisation",
                    "title": "Foreign, Commonwealth & Development Office",
                    "web_url": "https://www.gov.uk/government/organisations/foreign-commonwealth-development-office",
                    "withdrawn": false
                }
            ],
            "parent": [
                {
                    "api_path": "/api/content/foreign-travel-advice",
                    "api_url": "https://www.gov.uk/api/content/foreign-travel-advice",
                    "base_path": "/foreign-travel-advice",
                    "content_id": "08d48cdd-6b50-43ff-a53b-beab47f4aab0",
                    "document_type": "travel_advice_index",
                    "links": {
                        "parent": [
                            {
                                "api_path": "/api/content/browse/abroad/travel-abroad",
                                "api_url": "https://www.gov.uk/api/content/browse/abroad/travel-abroad",
                                "base_path": "/browse/abroad/travel-abroad",
                                "content_id": "b9849cd6-61a7-42dc-8124-362d2c7d48b0",
                                "description": "Includes the latest travel advice by country, your rights at the airport and getting help abroad",
                                "document_type": "mainstream_browse_page",
                                "links": {
                                    "parent": [
                                        {
                                            "api_path": "/api/content/browse/abroad",
                                            "api_url": "https://www.gov.uk/api/content/browse/abroad",
                                            "base_path": "/browse/abroad",
                                            "content_id": "86eb717a-fb40-42e7-83fa-d031a03880fb",
                                            "description": "Includes renewing passports and travel advice by country",
                                            "document_type": "mainstream_browse_page",
                                            "links": {},
                                            "locale": "en",
                                            "public_updated_at": "2015-04-08T10:48:43Z",
                                            "schema_name": "mainstream_browse_page",
                                            "title": "Passports, travel and living abroad",
                                            "web_url": "https://www.gov.uk/browse/abroad",
                                            "withdrawn": false
                                        }
                                    ]
                                },
                                "locale": "en",
                                "public_updated_at": "2023-09-22T09:55:27Z",
                                "schema_name": "mainstream_browse_page",
                                "title": "Travel abroad",
                                "web_url": "https://www.gov.uk/browse/abroad/travel-abroad",
                                "withdrawn": false
                            }
                        ]
                    },
                    "locale": "en",
                    "public_updated_at": "2020-03-10T13:33:58Z",
                    "schema_name": "travel_advice_index",
                    "title": "Foreign travel advice",
                    "web_url": "https://www.gov.uk/foreign-travel-advice",
                    "withdrawn": false
                }
            ],
            "primary_publishing_organisation": [
                {
                    "analytics_identifier": "D1315",
                    "api_path": "/api/content/government/organisations/foreign-commonwealth-development-office",
                    "api_url": "https://www.gov.uk/api/content/government/organisations/foreign-commonwealth-development-office",
                    "base_path": "/government/organisations/foreign-commonwealth-development-office",
                    "content_id": "f9fcf3fe-2751-4dca-97ca-becaeceb4b26",
                    "details": {
                        "acronym": "FCDO",
                        "brand": "foreign-commonwealth-development-office",
                        "default_news_image": {
                            "high_resolution_url": "https://assets.publishing.service.gov.uk/media/621e4de4e90e0710be0354d7/s960_fcdo-main-building.jpg",
                            "url": "https://assets.publishing.service.gov.uk/media/621e4de48fa8f5490aff83b4/s300_fcdo-main-building.jpg"
                        },
                        "logo": {
                            "crest": "single-identity",
                            "formatted_title": "Foreign, Commonwealth<br/>&amp; Development Office"
                        },
                        "organisation_govuk_status": {
                            "status": "live",
                            "updated_at": null,
                            "url": null
                        }
                    },
                    "document_type": "organisation",
                    "links": {},
                    "locale": "en",
                    "schema_name": "organisation",
                    "title": "Foreign, Commonwealth & Development Office",
                    "web_url": "https://www.gov.uk/government/organisations/foreign-commonwealth-development-office",
                    "withdrawn": false
                }
            ],
            "related": [
                {
                    "api_path": "/api/content/browse/abroad/travel-abroad",
                    "api_url": "https://www.gov.uk/api/content/browse/abroad/travel-abroad",
                    "base_path": "/browse/abroad/travel-abroad",
                    "content_id": "b9849cd6-61a7-42dc-8124-362d2c7d48b0",
                    "description": "Includes the latest travel advice by country, your rights at the airport and getting help abroad",
                    "document_type": "mainstream_browse_page",
                    "links": {},
                    "locale": "en",
                    "public_updated_at": "2023-09-22T09:55:27Z",
                    "schema_name": "mainstream_browse_page",
                    "title": "Travel abroad",
                    "web_url": "https://www.gov.uk/browse/abroad/travel-abroad",
                    "withdrawn": false
                },
                {
                    "api_path": "/api/content/hand-luggage-restrictions",
                    "api_url": "https://www.gov.uk/api/content/hand-luggage-restrictions",
                    "base_path": "/hand-luggage-restrictions",
                    "content_id": "95f9c380-30bc-44c7-86b4-e9c9ef0fc272",
                    "document_type": "guide",
                    "links": {},
                    "locale": "en",
                    "public_updated_at": "2015-09-07T16:23:07Z",
                    "schema_name": "guide",
                    "title": "Hand luggage restrictions at UK airports",
                    "web_url": "https://www.gov.uk/hand-luggage-restrictions",
                    "withdrawn": false
                },
                {
                    "api_path": "/api/content/driving-abroad",
                    "api_url": "https://www.gov.uk/api/content/driving-abroad",
                    "base_path": "/driving-abroad",
                    "content_id": "e4d06cb9-9e2e-4e82-b802-0aad013ae16c",
                    "document_type": "guide",
                    "links": {},
                    "locale": "en",
                    "public_updated_at": "2015-07-09T08:31:23Z",
                    "schema_name": "guide",
                    "title": "Driving abroad",
                    "web_url": "https://www.gov.uk/driving-abroad",
                    "withdrawn": false
                },
                {
                    "api_path": "/api/content/browse/abroad",
                    "api_url": "https://www.gov.uk/api/content/browse/abroad",
                    "base_path": "/browse/abroad",
                    "content_id": "86eb717a-fb40-42e7-83fa-d031a03880fb",
                    "description": "Includes renewing passports and travel advice by country",
                    "document_type": "mainstream_browse_page",
                    "links": {},
                    "locale": "en",
                    "public_updated_at": "2015-04-08T10:48:43Z",
                    "schema_name": "mainstream_browse_page",
                    "title": "Passports, travel and living abroad",
                    "web_url": "https://www.gov.uk/browse/abroad",
                    "withdrawn": false
                },
                {
                    "api_path": "/api/content/renew-adult-passport",
                    "api_url": "https://www.gov.uk/api/content/renew-adult-passport",
                    "base_path": "/renew-adult-passport",
                    "content_id": "82248bb1-c4d6-41e0-9494-d98123475626",
                    "document_type": "guide",
                    "links": {},
                    "locale": "en",
                    "public_updated_at": "2015-01-12T00:01:07Z",
                    "schema_name": "guide",
                    "title": "Renew or replace your adult passport",
                    "web_url": "https://www.gov.uk/renew-adult-passport",
                    "withdrawn": false
                }
            ],
            "suggested_ordered_related_items": [
                {
                    "api_path": "/api/content/foreign-travel-advice/serbia",
                    "api_url": "https://www.gov.uk/api/content/foreign-travel-advice/serbia",
                    "base_path": "/foreign-travel-advice/serbia",
                    "content_id": "e21957c3-680e-4b4a-bc04-589abc3a2b60",
                    "details": {
                        "change_description": "This travel advice has been rewritten to make it easier to read and understand.",
                        "country": {
                            "name": "Serbia",
                            "slug": "serbia",
                            "synonyms": []
                        }
                    },
                    "document_type": "travel_advice",
                    "links": {},
                    "locale": "en",
                    "public_updated_at": "2023-08-15T14:29:50Z",
                    "schema_name": "travel_advice",
                    "title": "Serbia travel advice",
                    "web_url": "https://www.gov.uk/foreign-travel-advice/serbia",
                    "withdrawn": false
                },
                {
                    "api_path": "/api/content/foreign-travel-advice/albania",
                    "api_url": "https://www.gov.uk/api/content/foreign-travel-advice/albania",
                    "base_path": "/foreign-travel-advice/albania",
                    "content_id": "2a3938e1-d588-45fc-8c8f-0f51814d5409",
                    "details": {
                        "change_description": "This travel advice has been rewritten to make it easier to read and understand.",
                        "country": {
                            "name": "Albania",
                            "slug": "albania",
                            "synonyms": []
                        }
                    },
                    "document_type": "travel_advice",
                    "links": {},
                    "locale": "en",
                    "public_updated_at": "2023-09-19T10:04:37Z",
                    "schema_name": "travel_advice",
                    "title": "Albania travel advice",
                    "web_url": "https://www.gov.uk/foreign-travel-advice/albania",
                    "withdrawn": false
                },
                {
                    "api_path": "/api/content/foreign-travel-advice/kosovo",
                    "api_url": "https://www.gov.uk/api/content/foreign-travel-advice/kosovo",
                    "base_path": "/foreign-travel-advice/kosovo",
                    "content_id": "261a33bd-bf2f-401e-b5e1-31d0b085f4ae",
                    "details": {
                        "change_description": "This travel advice has been rewritten to make it easier to read and understand. ",
                        "country": {
                            "name": "Kosovo",
                            "slug": "kosovo",
                            "synonyms": []
                        }
                    },
                    "document_type": "travel_advice",
                    "links": {},
                    "locale": "en",
                    "public_updated_at": "2023-09-12T12:06:22Z",
                    "schema_name": "travel_advice",
                    "title": "Kosovo travel advice",
                    "web_url": "https://www.gov.uk/foreign-travel-advice/kosovo",
                    "withdrawn": false
                },
                {
                    "api_path": "/api/content/foreign-travel-advice/syria",
                    "api_url": "https://www.gov.uk/api/content/foreign-travel-advice/syria",
                    "base_path": "/foreign-travel-advice/syria",
                    "content_id": "85c16f75-3380-497e-a915-4d77256cde37",
                    "details": {
                        "change_description": "Information on a 7.8 major earthquake that hit the Gazientep region of Southeast Turkey on 6 February 2023 which has also severely impacted cities in Northern Syria including Idlib and Aleppo ('Summary' page).",
                        "country": {
                            "name": "Syria",
                            "slug": "syria",
                            "synonyms": []
                        }
                    },
                    "document_type": "travel_advice",
                    "links": {},
                    "locale": "en",
                    "public_updated_at": "2023-02-06T15:30:45Z",
                    "schema_name": "travel_advice",
                    "title": "Syria travel advice",
                    "web_url": "https://www.gov.uk/foreign-travel-advice/syria",
                    "withdrawn": false
                },
                {
                    "api_path": "/api/content/foreign-travel-advice/oman",
                    "api_url": "https://www.gov.uk/api/content/foreign-travel-advice/oman",
                    "base_path": "/foreign-travel-advice/oman",
                    "content_id": "aa62bc84-6fd0-4665-8b9a-4c4ab5977e8a",
                    "details": {
                        "change_description": "Removal of reference to Tropical Cyclone Tej and update on wadi flash floods ('Natural disasters' page).",
                        "country": {
                            "name": "Oman",
                            "slug": "oman",
                            "synonyms": []
                        }
                    },
                    "document_type": "travel_advice",
                    "links": {},
                    "locale": "en",
                    "public_updated_at": "2023-10-26T10:36:43Z",
                    "schema_name": "travel_advice",
                    "title": "Oman travel advice",
                    "web_url": "https://www.gov.uk/foreign-travel-advice/oman",
                    "withdrawn": false
                }
            ],
            "taxons": [
                {
                    "api_path": "/api/content/world/living-in-macedonia",
                    "api_url": "https://www.gov.uk/api/content/world/living-in-macedonia",
                    "base_path": "/world/living-in-macedonia",
                    "content_id": "ed81beb6-8427-41a4-849c-76cbf109cd0c",
                    "description": "Includes how to access healthcare, get a document legalised, lists of lawyers and how to vote abroad.",
                    "details": {
                        "internal_name": "Living in North Macedonia",
                        "notes_for_editors": "",
                        "visible_to_departmental_editors": false
                    },
                    "document_type": "taxon",
                    "links": {
                        "parent_taxons": [
                            {
                                "api_path": "/api/content/world/north-macedonia",
                                "api_url": "https://www.gov.uk/api/content/world/north-macedonia",
                                "base_path": "/world/north-macedonia",
                                "content_id": "b4c8cc2b-0fb0-4ec0-ba63-72c324f51b3a",
                                "description": "Services if you're visiting, studying, working or living in North Macedonia. Includes information about trading with and doing business in the UK and North Macedonia.",
                                "details": {
                                    "internal_name": "UK help and services in North Macedonia",
                                    "notes_for_editors": "",
                                    "visible_to_departmental_editors": false
                                },
                                "document_type": "taxon",
                                "links": {
                                    "parent_taxons": [
                                        {
                                            "api_path": "/api/content/world/all",
                                            "api_url": "https://www.gov.uk/api/content/world/all",
                                            "base_path": "/world/all",
                                            "content_id": "91b8ef20-74e7-4552-880c-50e6d73c2ff9",
                                            "description": "Help and services in a country",
                                            "details": {
                                                "internal_name": "Help and services around the world",
                                                "notes_for_editors": "",
                                                "url_override": "",
                                                "visible_to_departmental_editors": false
                                            },
                                            "document_type": "taxon",
                                            "links": {},
                                            "locale": "en",
                                            "phase": "live",
                                            "public_updated_at": "2021-07-09T10:08:54Z",
                                            "schema_name": "taxon",
                                            "title": "Help and services around the world",
                                            "web_url": "https://www.gov.uk/world/all",
                                            "withdrawn": false
                                        }
                                    ]
                                },
                                "locale": "en",
                                "phase": "live",
                                "public_updated_at": "2019-02-22T17:11:25Z",
                                "schema_name": "taxon",
                                "title": "UK help and services in North Macedonia",
                                "web_url": "https://www.gov.uk/world/north-macedonia",
                                "withdrawn": false
                            }
                        ]
                    },
                    "locale": "en",
                    "phase": "live",
                    "public_updated_at": "2019-02-18T12:48:18Z",
                    "schema_name": "taxon",
                    "title": "Living in North Macedonia",
                    "web_url": "https://www.gov.uk/world/living-in-macedonia",
                    "withdrawn": false
                },
                {
                    "api_path": "/api/content/world/travelling-to-macedonia",
                    "api_url": "https://www.gov.uk/api/content/world/travelling-to-macedonia",
                    "base_path": "/world/travelling-to-macedonia",
                    "content_id": "f2187875-e699-4117-86cf-dedcd1bceac5",
                    "description": "Includes travel advice and how to get married abroad.",
                    "details": {
                        "internal_name": "Travelling to North Macedonia",
                        "notes_for_editors": "",
                        "visible_to_departmental_editors": false
                    },
                    "document_type": "taxon",
                    "links": {
                        "parent_taxons": [
                            {
                                "api_path": "/api/content/world/north-macedonia",
                                "api_url": "https://www.gov.uk/api/content/world/north-macedonia",
                                "base_path": "/world/north-macedonia",
                                "content_id": "b4c8cc2b-0fb0-4ec0-ba63-72c324f51b3a",
                                "description": "Services if you're visiting, studying, working or living in North Macedonia. Includes information about trading with and doing business in the UK and North Macedonia.",
                                "details": {
                                    "internal_name": "UK help and services in North Macedonia",
                                    "notes_for_editors": "",
                                    "visible_to_departmental_editors": false
                                },
                                "document_type": "taxon",
                                "links": {
                                    "parent_taxons": [
                                        {
                                            "api_path": "/api/content/world/all",
                                            "api_url": "https://www.gov.uk/api/content/world/all",
                                            "base_path": "/world/all",
                                            "content_id": "91b8ef20-74e7-4552-880c-50e6d73c2ff9",
                                            "description": "Help and services in a country",
                                            "details": {
                                                "internal_name": "Help and services around the world",
                                                "notes_for_editors": "",
                                                "url_override": "",
                                                "visible_to_departmental_editors": false
                                            },
                                            "document_type": "taxon",
                                            "links": {},
                                            "locale": "en",
                                            "phase": "live",
                                            "public_updated_at": "2021-07-09T10:08:54Z",
                                            "schema_name": "taxon",
                                            "title": "Help and services around the world",
                                            "web_url": "https://www.gov.uk/world/all",
                                            "withdrawn": false
                                        }
                                    ]
                                },
                                "locale": "en",
                                "phase": "live",
                                "public_updated_at": "2019-02-22T17:11:25Z",
                                "schema_name": "taxon",
                                "title": "UK help and services in North Macedonia",
                                "web_url": "https://www.gov.uk/world/north-macedonia",
                                "withdrawn": false
                            }
                        ]
                    },
                    "locale": "en",
                    "phase": "live",
                    "public_updated_at": "2019-02-18T12:47:12Z",
                    "schema_name": "taxon",
                    "title": "Travelling to North Macedonia",
                    "web_url": "https://www.gov.uk/world/travelling-to-macedonia",
                    "withdrawn": false
                }
            ]
        },
        "locale": "en",
        "phase": "live",
        "public_updated_at": "2023-08-14T15:49:13Z",
        "publishing_app": "travel-advice-publisher",
        "publishing_request_id": "21-1692028153.889-10.13.20.161-26258",
        "publishing_scheduled_at": null,
        "rendering_app": "government-frontend",
        "scheduled_publishing_delay_seconds": null,
        "schema_name": "travel_advice",
        "title": "North Macedonia travel advice",
        "updated_at": "2023-11-15T10:47:08Z",
        "withdrawn_notice": {}
    }
}